airflow_config/__init__.py
airflow_config/airflow_local_settings.py
airflow_config/webserver_ldap.py
airflow_config/plugins/__init__.py
airflow_config/plugins/XCom/__init__.py
airflow_config/plugins/XCom/gce_xcom_backend.py
cornflow/__init__.py
cornflow/app.py
cornflow/config.py
cornflow/gunicorn.py
cornflow/cli/__init__.py
cornflow/cli/actions.py
cornflow/cli/arguments.py
cornflow/cli/config.py
cornflow/cli/migrations.py
cornflow/cli/permissions.py
cornflow/cli/roles.py
cornflow/cli/schemas.py
cornflow/cli/service.py
cornflow/cli/users.py
cornflow/cli/utils.py
cornflow/cli/views.py
cornflow/cli/tools/__init__.py
cornflow/cli/tools/api_generator.py
cornflow/cli/tools/endpoint_tools.py
cornflow/cli/tools/models_tools.py
cornflow/cli/tools/schema_generator.py
cornflow/cli/tools/schemas_tools.py
cornflow/cli/tools/tools.py
cornflow/commands/__init__.py
cornflow/commands/access.py
cornflow/commands/actions.py
cornflow/commands/auxiliar.py
cornflow/commands/cleanup.py
cornflow/commands/dag.py
cornflow/commands/permissions.py
cornflow/commands/roles.py
cornflow/commands/schemas.py
cornflow/commands/users.py
cornflow/commands/views.py
cornflow/endpoints/__init__.py
cornflow/endpoints/action.py
cornflow/endpoints/alarms.py
cornflow/endpoints/apiview.py
cornflow/endpoints/case.py
cornflow/endpoints/dag.py
cornflow/endpoints/data_check.py
cornflow/endpoints/example_data.py
cornflow/endpoints/execution.py
cornflow/endpoints/health.py
cornflow/endpoints/instance.py
cornflow/endpoints/licenses.py
cornflow/endpoints/login.py
cornflow/endpoints/main_alarms.py
cornflow/endpoints/meta_resource.py
cornflow/endpoints/permission.py
cornflow/endpoints/roles.py
cornflow/endpoints/schemas.py
cornflow/endpoints/signup.py
cornflow/endpoints/tables.py
cornflow/endpoints/token.py
cornflow/endpoints/user.py
cornflow/endpoints/user_role.py
cornflow/migrations/README
cornflow/migrations/alembic.ini
cornflow/migrations/env.py
cornflow/migrations/script.py.mako
cornflow-1.2.5.dist-info/METADATA
cornflow-1.2.5.dist-info/WHEEL
cornflow-1.2.5.dist-info/entry_points.txt
cornflow-1.2.5.dist-info/top_level.txt
cornflow-1.2.5.dist-info/RECORD
