Metadata-Version: 2.4
Name: cornflow
Version: 1.2.5
Summary: cornflow is an open source multi-solver optimization server with a REST API built using flask.
Home-page: https://github.com/baobabsoluciones/cornflow
Author: baobab soluciones
Author-email: cornflow@baobabsoluciones.es
Classifier: Programming Language :: Python :: 3
Classifier: License :: OSI Approved :: Apache Software License
Classifier: Operating System :: OS Independent
Classifier: Development Status :: 5 - Production/Stable
Requires-Python: >=3.9
Requires-Dist: alembic==1.9.2
Requires-Dist: apispec<=6.3.0
Requires-Dist: cachetools==5.3.3
Requires-Dist: click<=8.1.7
Requires-Dist: cornflow-client<=1.2.5
Requires-Dist: cryptography<=44.0.1
Requires-Dist: disposable-email-domains>=0.0.86
Requires-Dist: Flask==2.3.2
Requires-Dist: flask-apispec<=0.11.4
Requires-Dist: Flask-Bcrypt<=1.0.1
Requires-Dist: Flask-Compress<=1.14
Requires-Dist: flask-cors>=4.0.2
Requires-Dist: flask-inflate<=0.3
Requires-Dist: Flask-Migrate<=4.0.5
Requires-Dist: Flask-RESTful<=0.3.10
Requires-Dist: Flask-SQLAlchemy==2.5.1
Requires-Dist: gevent==23.9.1
Requires-Dist: greenlet<=2.0.2; python_version < "3.11"
Requires-Dist: greenlet==3.0.3; python_version >= "3.11"
Requires-Dist: gunicorn<=23.0.0
Requires-Dist: jsonpatch<=1.33
Requires-Dist: ldap3<=2.9.1
Requires-Dist: marshmallow<=3.20.2
Requires-Dist: PuLP<=2.9.0
Requires-Dist: psycopg2<=2.9.9
Requires-Dist: PyJWT<=2.8.0
Requires-Dist: pytups>=0.86.2
Requires-Dist: requests<=2.32.4
Requires-Dist: SQLAlchemy==1.3.21
Requires-Dist: webargs<=8.3.0
Requires-Dist: Werkzeug==3.0.6
Dynamic: author
Dynamic: author-email
Dynamic: classifier
Dynamic: description
Dynamic: home-page
Dynamic: requires-dist
Dynamic: requires-python
Dynamic: summary
